{"typeDefenses": [{"ability": "default", "types": {"rock": "\u00bd", "fighting": "0", "normal": "0", "fairy": "", "psychic": "", "dragon": "", "fire": "", "grass": "2", "dark": "2", "steel": "", "electric": "0", "ice": "2", "poison": "\u00bc", "flying": "", "ghost": "2", "ground": "", "bug": "\u00bd", "water": "2"}}], "breeding": {"eggGroups": ["Amorphous"], "cycles": 15, "male": 50, "female": 50}, "training": {"evYield": "1 Defense", "levelingRate": "Medium Fast", "happiness": 70, "exp": 64, "catchRate": 140}, "types": ["Ghost", "Ground"], "attackSets": {"learn": [{"level": "1", "category": "special", "power": "20", "type": "Grass", "name": "Absorb", "accuracy": "100"}, {"level": "1", "category": "status", "power": "\u2014", "type": "Normal", "name": "Harden", "accuracy": "\u2014"}, {"level": "5", "category": "physical", "power": "30", "type": "Ghost", "name": "Astonish", "accuracy": "100"}, {"level": "9", "category": "status", "power": "\u2014", "type": "Ground", "name": "Sand Attack", "accuracy": "100"}, {"level": "14", "category": "physical", "power": "35", "type": "Ground", "name": "Sand Tomb", "accuracy": "85"}, {"level": "18", "category": "special", "power": "40", "type": "Grass", "name": "Mega Drain", "accuracy": "100"}, {"level": "23", "category": "physical", "power": "60", "type": "Ground", "name": "Bulldoze", "accuracy": "100"}, {"level": "27", "category": "status", "power": "\u2014", "type": "Psychic", "name": "Hypnosis", "accuracy": "60"}, {"level": "32", "category": "status", "power": "\u2014", "type": "Steel", "name": "Iron Defense", "accuracy": "\u2014"}, {"level": "36", "category": "special", "power": "75", "type": "Grass", "name": "Giga Drain", "accuracy": "100"}, {"level": "41", "category": "special", "power": "80", "type": "Ghost", "name": "Shadow Ball", "accuracy": "100"}, {"level": "45", "category": "special", "power": "90", "type": "Ground", "name": "Earth Power", "accuracy": "100"}, {"level": "50", "category": "status", "power": "\u2014", "type": "Ground", "name": "Shore Up", "accuracy": "\u2014"}, {"level": "54", "category": "status", "power": "\u2014", "type": "Rock", "name": "Sandstorm", "accuracy": "\u2014"}], "tutor": [], "breed": [{"power": "\u2014", "category": "status", "type": "Psychic", "name": "Amnesia", "accuracy": "\u2014"}, {"power": "60", "category": "special", "type": "Rock", "name": "Ancient Power", "accuracy": "100"}, {"power": "\u2014", "category": "status", "type": "Ghost", "name": "Destiny Bond", "accuracy": "\u2014"}, {"power": "\u2014", "category": "special", "type": "Normal", "name": "Spit Up", "accuracy": "100"}, {"power": "\u2014", "category": "status", "type": "Normal", "name": "Stockpile", "accuracy": "\u2014"}, {"power": "\u2014", "category": "status", "type": "Normal", "name": "Swallow", "accuracy": "\u2014"}], "tm": [{"tm": "6", "category": "status", "power": "\u2014", "type": "Poison", "name": "Toxic", "accuracy": "90"}, {"tm": "10", "category": "special", "power": "60", "type": "Normal", "name": "Hidden Power", "accuracy": "100"}, {"tm": "17", "category": "status", "power": "\u2014", "type": "Normal", "name": "Protect", "accuracy": "\u2014"}, {"tm": "21", "category": "physical", "power": "\u2014", "type": "Normal", "name": "Frustration", "accuracy": "100"}, {"tm": "26", "category": "physical", "power": "100", "type": "Ground", "name": "Earthquake", "accuracy": "100"}, {"tm": "27", "category": "physical", "power": "\u2014", "type": "Normal", "name": "Return", "accuracy": "100"}, {"tm": "29", "category": "special", "power": "90", "type": "Psychic", "name": "Psychic", "accuracy": "100"}, {"tm": "30", "category": "special", "power": "80", "type": "Ghost", "name": "Shadow Ball", "accuracy": "100"}, {"tm": "32", "category": "status", "power": "\u2014", "type": "Normal", "name": "Double Team", "accuracy": "\u2014"}, {"tm": "37", "category": "status", "power": "\u2014", "type": "Rock", "name": "Sandstorm", "accuracy": "\u2014"}, {"tm": "39", "category": "physical", "power": "60", "type": "Rock", "name": "Rock Tomb", "accuracy": "95"}, {"tm": "42", "category": "physical", "power": "70", "type": "Normal", "name": "Facade", "accuracy": "100"}, {"tm": "44", "category": "status", "power": "\u2014", "type": "Psychic", "name": "Rest", "accuracy": "\u2014"}, {"tm": "45", "category": "status", "power": "\u2014", "type": "Normal", "name": "Attract", "accuracy": "100"}, {"tm": "48", "category": "special", "power": "60", "type": "Normal", "name": "Round", "accuracy": "100"}, {"tm": "53", "category": "special", "power": "90", "type": "Grass", "name": "Energy Ball", "accuracy": "100"}, {"tm": "69", "category": "status", "power": "\u2014", "type": "Rock", "name": "Rock Polish", "accuracy": "\u2014"}, {"tm": "71", "category": "physical", "power": "100", "type": "Rock", "name": "Stone Edge", "accuracy": "80"}, {"tm": "78", "category": "physical", "power": "60", "type": "Ground", "name": "Bulldoze", "accuracy": "100"}, {"tm": "80", "category": "physical", "power": "75", "type": "Rock", "name": "Rock Slide", "accuracy": "90"}, {"tm": "83", "category": "special", "power": "20", "type": "Bug", "name": "Infestation", "accuracy": "100"}, {"tm": "87", "category": "status", "power": "\u2014", "type": "Normal", "name": "Swagger", "accuracy": "85"}, {"tm": "88", "category": "status", "power": "\u2014", "type": "Normal", "name": "Sleep Talk", "accuracy": "\u2014"}, {"tm": "90", "category": "status", "power": "\u2014", "type": "Normal", "name": "Substitute", "accuracy": "\u2014"}, {"tm": "100", "category": "status", "power": "\u2014", "type": "Normal", "name": "Confide", "accuracy": "\u2014"}], "evolution": []}, "stats": {"spDef": {"base": 45, "max": 207, "min": 85}, "hp": {"base": 55, "max": 314, "min": 220}, "atk": {"base": 55, "max": 229, "min": 103}, "spAtk": {"base": 70, "max": 262, "min": 130}, "def": {"base": 80, "max": 284, "min": 148}, "spd": {"base": 15, "max": 141, "min": 31}}, "locations": ["Hano Beach"], "abilities": {"normal": ["Water Compaction"], "hidden": ["Sand Veil"]}, "evolutions": [], "name": "Sandygast"}