{"typeDefenses": [{"ability": "default", "types": {"rock": "2", "fighting": "", "normal": "", "fairy": "", "psychic": "", "dragon": "", "fire": "", "grass": "\u00bd", "dark": "", "steel": "", "electric": "2", "ice": "2", "poison": "", "flying": "", "ghost": "0", "ground": "0", "bug": "\u00bd", "water": ""}}], "breeding": {"eggGroups": ["Flying"], "cycles": 15, "male": 50, "female": 50}, "training": {"evYield": "1 Speed", "levelingRate": "Medium Fast", "happiness": 70, "exp": 58, "catchRate": 255}, "types": ["Normal", "Flying"], "attackSets": {"learn": [{"level": "1", "category": "status", "power": "\u2014", "type": "Normal", "name": "Growl", "accuracy": "100"}, {"level": "1", "category": "physical", "power": "35", "type": "Flying", "name": "Peck", "accuracy": "100"}, {"level": "4", "category": "status", "power": "\u2014", "type": "Normal", "name": "Leer", "accuracy": "100"}, {"level": "8", "category": "physical", "power": "40", "type": "Dark", "name": "Pursuit", "accuracy": "100"}, {"level": "11", "category": "physical", "power": "15", "type": "Normal", "name": "Fury Attack", "accuracy": "85"}, {"level": "15", "category": "physical", "power": "60", "type": "Flying", "name": "Aerial Ace", "accuracy": "\u221e"}, {"level": "18", "category": "status", "power": "\u2014", "type": "Flying", "name": "Mirror Move", "accuracy": "\u2014"}, {"level": "22", "category": "physical", "power": "60", "type": "Dark", "name": "Assurance", "accuracy": "100"}, {"level": "25", "category": "status", "power": "\u2014", "type": "Psychic", "name": "Agility", "accuracy": "\u2014"}, {"level": "29", "category": "status", "power": "\u2014", "type": "Normal", "name": "Focus Energy", "accuracy": "\u2014"}, {"level": "32", "category": "status", "power": "\u2014", "type": "Flying", "name": "Roost", "accuracy": "\u2014"}, {"level": "36", "category": "physical", "power": "80", "type": "Flying", "name": "Drill Peck", "accuracy": "100"}], "tutor": [], "breed": [{"power": "30", "category": "physical", "type": "Ghost", "name": "Astonish", "accuracy": "100"}, {"power": "\u2014", "category": "status", "type": "Flying", "name": "Feather Dance", "accuracy": "100"}, {"power": "60", "category": "physical", "type": "Dark", "name": "Feint Attack", "accuracy": "\u221e"}, {"power": "40", "category": "physical", "type": "Normal", "name": "Quick Attack", "accuracy": "100"}, {"power": "80", "category": "special", "type": "Normal", "name": "Razor Wind", "accuracy": "100"}, {"power": "\u2014", "category": "status", "type": "Normal", "name": "Scary Face", "accuracy": "100"}, {"power": "140", "category": "physical", "type": "Flying", "name": "Sky Attack", "accuracy": "90"}, {"power": "70", "category": "physical", "type": "Steel", "name": "Steel Wing", "accuracy": "90"}, {"power": "80", "category": "special", "type": "Normal", "name": "Tri Attack", "accuracy": "100"}, {"power": "90", "category": "special", "type": "Normal", "name": "Uproar", "accuracy": "100"}, {"power": "\u2014", "category": "status", "type": "Normal", "name": "Whirlwind", "accuracy": "\u2014"}], "tm": [{"tm": "1", "category": "status", "power": "\u2014", "type": "Normal", "name": "Work Up", "accuracy": "\u2014"}, {"tm": "6", "category": "status", "power": "\u2014", "type": "Poison", "name": "Toxic", "accuracy": "90"}, {"tm": "10", "category": "special", "power": "60", "type": "Normal", "name": "Hidden Power", "accuracy": "100"}, {"tm": "11", "category": "status", "power": "\u2014", "type": "Fire", "name": "Sunny Day", "accuracy": "\u2014"}, {"tm": "17", "category": "status", "power": "\u2014", "type": "Normal", "name": "Protect", "accuracy": "\u2014"}, {"tm": "18", "category": "status", "power": "\u2014", "type": "Water", "name": "Rain Dance", "accuracy": "\u2014"}, {"tm": "19", "category": "status", "power": "\u2014", "type": "Flying", "name": "Roost", "accuracy": "\u2014"}, {"tm": "21", "category": "physical", "power": "\u2014", "type": "Normal", "name": "Frustration", "accuracy": "100"}, {"tm": "27", "category": "physical", "power": "\u2014", "type": "Normal", "name": "Return", "accuracy": "100"}, {"tm": "32", "category": "status", "power": "\u2014", "type": "Normal", "name": "Double Team", "accuracy": "\u2014"}, {"tm": "40", "category": "physical", "power": "60", "type": "Flying", "name": "Aerial Ace", "accuracy": "\u221e"}, {"tm": "42", "category": "physical", "power": "70", "type": "Normal", "name": "Facade", "accuracy": "100"}, {"tm": "44", "category": "status", "power": "\u2014", "type": "Psychic", "name": "Rest", "accuracy": "\u2014"}, {"tm": "45", "category": "status", "power": "\u2014", "type": "Normal", "name": "Attract", "accuracy": "100"}, {"tm": "46", "category": "physical", "power": "60", "type": "Dark", "name": "Thief", "accuracy": "100"}, {"tm": "48", "category": "special", "power": "60", "type": "Normal", "name": "Round", "accuracy": "100"}, {"tm": "49", "category": "special", "power": "40", "type": "Normal", "name": "Echoed Voice", "accuracy": "100"}, {"tm": "51", "category": "physical", "power": "70", "type": "Steel", "name": "Steel Wing", "accuracy": "90"}, {"tm": "54", "category": "physical", "power": "40", "type": "Normal", "name": "False Swipe", "accuracy": "100"}, {"tm": "76", "category": "physical", "power": "90", "type": "Flying", "name": "Fly", "accuracy": "95"}, {"tm": "87", "category": "status", "power": "\u2014", "type": "Normal", "name": "Swagger", "accuracy": "85"}, {"tm": "88", "category": "status", "power": "\u2014", "type": "Normal", "name": "Sleep Talk", "accuracy": "\u2014"}, {"tm": "89", "category": "physical", "power": "70", "type": "Bug", "name": "U-turn", "accuracy": "100"}, {"tm": "90", "category": "status", "power": "\u2014", "type": "Normal", "name": "Substitute", "accuracy": "\u2014"}, {"tm": "100", "category": "status", "power": "\u2014", "type": "Normal", "name": "Confide", "accuracy": "\u2014"}], "evolution": []}, "stats": {"spDef": {"base": 31, "max": 177, "min": 60}, "hp": {"base": 40, "max": 284, "min": 190}, "atk": {"base": 60, "max": 240, "min": 112}, "spAtk": {"base": 31, "max": 177, "min": 60}, "def": {"base": 30, "max": 174, "min": 58}, "spd": {"base": 70, "max": 262, "min": 130}}, "locations": ["Route 2", "3"], "abilities": {"normal": ["Keen Eye"], "hidden": ["Sniper"]}, "evolutions": [], "name": "Spearow"}